p2psimpy/__init__.py
p2psimpy/config.py
p2psimpy/consts.py
p2psimpy/defaults.py
p2psimpy/logger.py
p2psimpy/messages.py
p2psimpy/network.py
p2psimpy/peer.py
p2psimpy/peer_factory.py
p2psimpy/services/__init__.py
p2psimpy/services/base.py
p2psimpy/services/connection_manager.py
p2psimpy/services/disruption.py
p2psimpy/services/gossip.py
p2psimpy/services/message_producer.py
p2psimpy/simulation.py
p2psimpy/utils.py
p2psimpy-0.1.0.dist-info/WHEEL
p2psimpy-0.1.0.dist-info/METADATA
p2psimpy-0.1.0.dist-info/RECORD
