Metadata-Version: 2.1
Name: p2psimpy
Version: 0.1.0
Summary: Event simulator for peer-to-peer experiments
Home-page: https://github.com/grimadas/p2psimpy
License: MIT
Author: grimadas
Author-email: bulat.nasrulin@gmail.com
Requires-Python: >=3.8,<3.11
Classifier: License :: OSI Approved :: MIT License
Classifier: Programming Language :: Python :: 3
Classifier: Programming Language :: Python :: 3.10
Classifier: Programming Language :: Python :: 3.8
Classifier: Programming Language :: Python :: 3.9
Requires-Dist: PyYAML (>=6.0,<7.0)
Requires-Dist: networkx (>=2.6.3,<3.0.0)
Requires-Dist: scipy (>=1.7.3,<2.0.0)
Requires-Dist: simpy (>=4.0.1,<5.0.0)
Project-URL: Repository, https://github.com/grimadas/p2psimpy
